resources/logo.svg
www/homepage.py
www/static/logo.png
xlsxcessive/__init__.py
xlsxcessive/cache.py
xlsxcessive/errors.py
xlsxcessive/markup.py
xlsxcessive/parts.py
xlsxcessive/style.py
xlsxcessive/workbook.py
xlsxcessive/worksheet.py
xlsxcessive/xlsx.py
xlsxcessive-1.1.3.dist-info/LICENSE
xlsxcessive-1.1.3.dist-info/METADATA
xlsxcessive-1.1.3.dist-info/WHEEL
xlsxcessive-1.1.3.dist-info/top_level.txt
xlsxcessive-1.1.3.dist-info/RECORD
