Metadata-Version: 2.1
Name: xlsxcessive
Version: 1.1.3
Summary: A Python library for writing .xlsx files.
Home-page: https://github.com/jaraco/xlsxcessive
Author: Christian Wyglendowski
Author-email: christian@dowski.com
Maintainer: Jason R. Coombs
Maintainer-email: jaraco@jaraco.com
Classifier: Development Status :: 5 - Production/Stable
Classifier: Intended Audience :: Developers
Classifier: License :: OSI Approved :: MIT License
Classifier: Programming Language :: Python :: 3
Classifier: Programming Language :: Python :: 3 :: Only
Requires-Python: >=3.7
License-File: LICENSE
Requires-Dist: openpack
Requires-Dist: singledispatchmethod ; python_version < "3.8"
Provides-Extra: docs
Requires-Dist: sphinx (>=3.5) ; extra == 'docs'
Requires-Dist: jaraco.packaging (>=9) ; extra == 'docs'
Requires-Dist: rst.linker (>=1.9) ; extra == 'docs'
Requires-Dist: furo ; extra == 'docs'
Provides-Extra: testing
Requires-Dist: pytest (>=6) ; extra == 'testing'
Requires-Dist: pytest-checkdocs (>=2.4) ; extra == 'testing'
Requires-Dist: flake8 (<5) ; extra == 'testing'
Requires-Dist: pytest-cov ; extra == 'testing'
Requires-Dist: pytest-enabler (>=1.3) ; extra == 'testing'
Requires-Dist: cherrypy ; extra == 'testing'
Requires-Dist: pytest-black (>=0.3.7) ; (platform_python_implementation != "PyPy") and extra == 'testing'
Requires-Dist: pytest-mypy (>=0.9.1) ; (platform_python_implementation != "PyPy") and extra == 'testing'
Requires-Dist: pytest-flake8 ; (python_version < "3.12") and extra == 'testing'
